[{"input": "story is to building what crust is to sandwich", "output": "", "score": 15819626.038708994}, {"input": "story is to building what shingle is to roof", "output": "", "score": 6977057.39292876}, {"input": "story is to building what data is to file", "output": "", "score": 13584306.640141886}, {"input": "story is to building what layer is to cake", "output": "", "score": 5045423.874230833}, {"input": "story is to building what root is to plant", "output": "", "score": 9060614.83761309}, {"input": "architect is to blueprint what instructor is to blackboard", "output": "", "score": 2151104.295790303}, {"input": "architect is to blueprint what graduate is to diploma", "output": "", "score": 17950335.86593958}, {"input": "architect is to blueprint what musician is to note", "output": "", "score": 8897927.052981298}, {"input": "architect is to blueprint what painter is to brush", "output": "", "score": 2734628.580809177}, {"input": "architect is to blueprint what composer is to score", "output": "", "score": 12669746.359670186}, {"input": "callow is to experience what painting is to artist", "output": "", "score": 10298469.55802538}, {"input": "callow is to experience what heavy is to weight", "output": "", "score": 11914344.0258575}, {"input": "callow is to experience what barren is to fruit", "output": "", "score": 1821998.2094894708}, {"input": "callow is to experience what gift is to donor", "output": "", "score": 12950185.549233321}, {"input": "callow is to experience what measure is to ounce", "output": "", "score": 8560885.553266287}, {"input": "embargo is to trade what umbrella is to clouds", "output": "", "score": 7601936.74855071}, {"input": "embargo is to trade what engine is to automobile", "output": "", "score": 10241342.738610636}, {"input": "embargo is to trade what license is to fishing", "output": "", "score": 17258921.63658021}, {"input": "embargo is to trade what alarm is to valuable", "output": "", "score": 22245920.251941863}, {"input": "embargo is to trade what helmet is to injury", "output": "", "score": 40360987.58898604}, {"input": "building is to blueprint what report is to outline", "output": "", "score": 29981886.610473912}, {"input": "building is to blueprint what chicken is to egg", "output": "", "score": 3759390.6266894885}, {"input": "building is to blueprint what brick is to wall", "output": "", "score": 2489866.7624716414}, {"input": "building is to blueprint what soup is to ladle", "output": "", "score": 4599329.671802096}, {"input": "building is to blueprint what conduit is to cement", "output": "", "score": 27985577.40247659}, {"input": "emend is to faulty what recruit is to competent", "output": "", "score": 9755802.769721255}, {"input": "emend is to faulty what fracture is to separable", "output": "", "score": 14500264.218629295}, {"input": "emend is to faulty what renovate is to habitable", "output": "", "score": 13000499.189797955}, {"input": "emend is to faulty what purify is to contaminated", "output": "", "score": 8132883.293941467}, {"input": "emend is to faulty what reproduce is to copied", "output": "", "score": 20155297.95141782}, {"input": "asteroid is to planet what quibble is to objection", "output": "", "score": 5451794.780367026}, {"input": "asteroid is to planet what gravel is to sand", "output": "", "score": 4516459.771774973}, {"input": "asteroid is to planet what mountain is to hill", "output": "", "score": 1853654.4734465014}, {"input": "asteroid is to planet what wood is to splinter", "output": "", "score": 6173462.205234452}, {"input": "asteroid is to planet what radio is to television", "output": "", "score": 1781752.7984689558}, {"input": "map is to navigate what manuscript is to submit", "output": "", "score": 32483874.987619814}, {"input": "map is to navigate what license is to revoke", "output": "", "score": 49194619.21717963}, {"input": "map is to navigate what writing is to erase", "output": "", "score": 14998012.96284902}, {"input": "map is to navigate what blueprint is to build", "output": "", "score": 3817360.102689802}, {"input": "map is to navigate what receipt is to pay", "output": "", "score": 4696900.618933109}, {"input": "epilogue is to book what sequel is to movie", "output": "", "score": 7831649.5597001}, {"input": "epilogue is to book what conclusion is to title", "output": "", "score": 13248814.291309891}, {"input": "epilogue is to book what tiff is to quarrel", "output": "", "score": 9014400.723306676}, {"input": "epilogue is to book what intermission is to play", "output": "", "score": 11232920.074478677}, {"input": "epilogue is to book what finale is to symphony", "output": "", "score": 20420498.72306543}, {"input": "raucous is to sound what dim is to light", "output": "", "score": 8234698.687001795}, {"input": "raucous is to sound what noisy is to uproar", "output": "", "score": 30960087.20835113}, {"input": "raucous is to sound what tanned is to leather", "output": "", "score": 15064343.385063898}, {"input": "raucous is to sound what rough is to texture", "output": "", "score": 11673136.841201473}, {"input": "raucous is to sound what hard is to granite", "output": "", "score": 7837665.947846333}, {"input": "eraser is to page what mop is to floor", "output": "", "score": 2804666.480413262}, {"input": "eraser is to page what sponge is to soap", "output": "", "score": 1412097.4002568112}, {"input": "eraser is to page what pen is to ink", "output": "", "score": 3699029.0809221184}, {"input": "eraser is to page what nail is to wall", "output": "", "score": 973149.80246146}, {"input": "eraser is to page what bleach is to stain", "output": "", "score": 3114111.966122102}, {"input": "levee is to flood what snow is to avalanche", "output": "", "score": 3662029.8141755057}, {"input": "levee is to flood what rain is to deluge", "output": "", "score": 1398349.4602766004}, {"input": "levee is to flood what immunization is to disease", "output": "", "score": 4916441.064122735}, {"input": "levee is to flood what zenith is to view", "output": "", "score": 8713467.508265855}, {"input": "levee is to flood what buttress is to building", "output": "", "score": 15487544.134415805}, {"input": "quack is to doctor what charlatan is to impostor", "output": "", "score": 57737850.794765}, {"input": "quack is to doctor what pretender is to monarch", "output": "", "score": 17589815.36046767}, {"input": "quack is to doctor what defendant is to prosecutor", "output": "", "score": 24354622.438083943}, {"input": "quack is to doctor what arbitrator is to judge", "output": "", "score": 15137415.54473038}, {"input": "quack is to doctor what professional is to amateur", "output": "", "score": 18660900.82928093}, {"input": "floral is to flowers what perennial is to plants", "output": "", "score": 2472143.9139354387}, {"input": "floral is to flowers what morbid is to cemeteries", "output": "", "score": 2878525.820311189}, {"input": "floral is to flowers what emotional is to feelings", "output": "", "score": 5220065.142295711}, {"input": "floral is to flowers what moral is to stories", "output": "", "score": 3693022.031837891}, {"input": "floral is to flowers what maniacal is to men", "output": "", "score": 4432986.548487023}, {"input": "decibel is to sound what ingredient is to food", "output": "", "score": 10497536.787603106}, {"input": "decibel is to sound what ruler is to length", "output": "", "score": 21190310.48110879}, {"input": "decibel is to sound what calories is to menu", "output": "", "score": 11219046.37807691}, {"input": "decibel is to sound what degree is to temperature", "output": "", "score": 9499317.380145589}, {"input": "decibel is to sound what headphones is to music", "output": "", "score": 26165952.95364229}, {"input": "amalgam is to metals what fracture is to bones", "output": "", "score": 13734183.37121022}, {"input": "amalgam is to metals what divorce is to marriages", "output": "", "score": 51550672.81683986}, {"input": "amalgam is to metals what coalition is to factions", "output": "", "score": 5164062.142861774}, {"input": "amalgam is to metals what car is to payments", "output": "", "score": 2596855.7601217735}, {"input": "amalgam is to metals what convention is to speeches", "output": "", "score": 31565585.512579978}, {"input": "emulate is to person what admire is to reputation", "output": "", "score": 15027294.773200674}, {"input": "emulate is to person what obey is to leader", "output": "", "score": 49819567.42366345}, {"input": "emulate is to person what cooperate is to partner", "output": "", "score": 11348609.758355593}, {"input": "emulate is to person what mimic is to gesture", "output": "", "score": 9940657.551112065}, {"input": "emulate is to person what mock is to sarcasm", "output": "", "score": 6436488.112665616}, {"input": "format is to newspaper what binding is to book", "output": "", "score": 1920833.3110843964}, {"input": "format is to newspaper what design is to building", "output": "", "score": 17131234.35892535}, {"input": "format is to newspaper what direction is to sign", "output": "", "score": 2873930.7118186746}, {"input": "format is to newspaper what market is to commodity", "output": "", "score": 4663168.673207098}, {"input": "format is to newspaper what catalogue is to library", "output": "", "score": 5115536.272441853}, {"input": "feign is to deceive what flee is to elude", "output": "", "score": 11304765.812093917}, {"input": "feign is to deceive what dangle is to drop", "output": "", "score": 34283814.17412056}, {"input": "feign is to deceive what send is to receive", "output": "", "score": 27377932.10869081}, {"input": "feign is to deceive what contract is to lengthen", "output": "", "score": 16945522.037832752}, {"input": "feign is to deceive what publish is to write", "output": "", "score": 53108076.35008067}, {"input": "flap is to wing what speak is to sound", "output": "", "score": 3131875.2734360443}, {"input": "flap is to wing what wave is to hand", "output": "", "score": 615173.4348739428}, {"input": "flap is to wing what whisper is to word", "output": "", "score": 6469989.93156857}, {"input": "flap is to wing what stub is to toe", "output": "", "score": 646210.078353586}, {"input": "flap is to wing what sing is to bird", "output": "", "score": 522372.36052904406}, {"input": "remuneration is to labor what gratuity is to bonus", "output": "", "score": 7557903.191098297}, {"input": "remuneration is to labor what apology is to regret", "output": "", "score": 12001779.731058814}, {"input": "remuneration is to labor what pledge is to donation", "output": "", "score": 10130672.857073545}, {"input": "remuneration is to labor what trophy is to victory", "output": "", "score": 26381600.201938458}, {"input": "remuneration is to labor what debt is to loan", "output": "", "score": 11219184.281224515}, {"input": "sequester is to juror what quarantine is to patient", "output": "", "score": 33700123.19832373}, {"input": "sequester is to juror what cloister is to convent", "output": "", "score": 46102790.02425909}, {"input": "sequester is to juror what parole is to prisoner", "output": "", "score": 21427331.02340197}, {"input": "sequester is to juror what graduate is to pupil", "output": "", "score": 30872863.03172482}, {"input": "sequester is to juror what elect is to mayor", "output": "", "score": 6377016.274221344}, {"input": "petal is to flower what oak is to tree", "output": "", "score": 7109634.774251525}, {"input": "petal is to flower what staple is to paper", "output": "", "score": 23720818.95993831}, {"input": "petal is to flower what sprout is to seed", "output": "", "score": 9516080.703121152}, {"input": "petal is to flower what tooth is to comb", "output": "", "score": 19427998.80140004}, {"input": "petal is to flower what tide is to beach", "output": "", "score": 3978219.0389648676}, {"input": "saunter is to walk what snore is to sleep", "output": "", "score": 2314117.590232385}, {"input": "saunter is to walk what drawl is to speak", "output": "", "score": 3728078.9678719924}, {"input": "saunter is to walk what throw is to toss", "output": "", "score": 2425340.9414007924}, {"input": "saunter is to walk what ladle is to brush", "output": "", "score": 3437384.2140783165}, {"input": "saunter is to walk what finish is to end", "output": "", "score": 2644259.6177867395}, {"input": "seed is to plant what pouch is to kangaroo", "output": "", "score": 8037430.095437907}, {"input": "seed is to plant what root is to soil", "output": "", "score": 4637642.023204676}, {"input": "seed is to plant what drop is to water", "output": "", "score": 5097127.451077014}, {"input": "seed is to plant what bark is to tree", "output": "", "score": 2659256.315661092}, {"input": "seed is to plant what egg is to bird", "output": "", "score": 3677285.1907579973}, {"input": "cooperation is to collusion what evidence is to proof", "output": "", "score": 61880134.043886244}, {"input": "cooperation is to collusion what achievement is to reward", "output": "", "score": 77495692.60952772}, {"input": "cooperation is to collusion what damage is to compensation", "output": "", "score": 19556298.666218992}, {"input": "cooperation is to collusion what imitation is to forgery", "output": "", "score": 32621215.768955953}, {"input": "cooperation is to collusion what emotion is to ecstasy", "output": "", "score": 41244544.65931992}, {"input": "lame is to mobility what lively is to energy", "output": "", "score": 2700962.6398058105}, {"input": "lame is to mobility what hostile is to enemy", "output": "", "score": 1178164.580980155}, {"input": "lame is to mobility what hoarse is to speech", "output": "", "score": 2919609.870779926}, {"input": "lame is to mobility what fractured is to cast", "output": "", "score": 10751112.082701026}, {"input": "lame is to mobility what walk is to transportation", "output": "", "score": 627398.1488005529}, {"input": "mechanical is to garage what artist is to canvas", "output": "", "score": 42933483.029908255}, {"input": "mechanical is to garage what administrator is to personnel", "output": "", "score": 50786125.585504204}, {"input": "mechanical is to garage what teller is to window", "output": "", "score": 41037222.97615161}, {"input": "mechanical is to garage what teacher is to information", "output": "", "score": 14921184.400889162}, {"input": "mechanical is to garage what nurse is to hospital", "output": "", "score": 13013950.522202449}, {"input": "lobbyist is to cause what legislator is to voter", "output": "", "score": 24072655.254077986}, {"input": "lobbyist is to cause what clergy is to congregation", "output": "", "score": 17504427.772075552}, {"input": "lobbyist is to cause what advertiser is to product", "output": "", "score": 8025813.111412435}, {"input": "lobbyist is to cause what defendant is to verdict", "output": "", "score": 18843631.557616197}, {"input": "lobbyist is to cause what consumer is to goods", "output": "", "score": 2713131.6159449113}, {"input": "birds is to wings what moose is to antlers", "output": "", "score": 4949429.334801846}, {"input": "birds is to wings what camel is to hump", "output": "", "score": 2570102.9862971124}, {"input": "birds is to wings what spider is to legs", "output": "", "score": 2080616.8371949284}, {"input": "birds is to wings what alligator is to tail", "output": "", "score": 10893264.745113362}, {"input": "birds is to wings what cat is to whiskers", "output": "", "score": 1845052.624877198}, {"input": "border is to country what current is to river", "output": "", "score": 12495442.87714285}, {"input": "border is to country what water is to lake", "output": "", "score": 2214363.9225877286}, {"input": "border is to country what waves is to sea", "output": "", "score": 9054488.60859767}, {"input": "border is to country what horizon is to sunset", "output": "", "score": 8657034.463038487}, {"input": "border is to country what shore is to ocean", "output": "", "score": 10669719.667474203}, {"input": "bankruptcy is to money what discrepancy is to account", "output": "", "score": 20254952.01325517}, {"input": "bankruptcy is to money what empathy is to feeling", "output": "", "score": 32726849.38441037}, {"input": "bankruptcy is to money what plan is to organization", "output": "", "score": 8370567.793611346}, {"input": "bankruptcy is to money what apathy is to caring", "output": "", "score": 8606285.608561838}, {"input": "bankruptcy is to money what homely is to household", "output": "", "score": 8957340.748603621}, {"input": "traffic is to street what ship is to gangplank", "output": "", "score": 4741229.285694661}, {"input": "traffic is to street what crop is to harvest", "output": "", "score": 4823472.206011265}, {"input": "traffic is to street what car is to garage", "output": "", "score": 5323443.062168298}, {"input": "traffic is to street what pedestrians is to feet", "output": "", "score": 2315190.399281337}, {"input": "traffic is to street what water is to riverbed", "output": "", "score": 4660176.211611953}, {"input": "throng is to people what game is to players", "output": "", "score": 6814293.790866955}, {"input": "throng is to people what picnic is to woods", "output": "", "score": 1559688.7468049475}, {"input": "throng is to people what swarm is to insects", "output": "", "score": 1814183.4923312003}, {"input": "throng is to people what cat is to kittens", "output": "", "score": 2638596.768071115}, {"input": "throng is to people what vase is to flowers", "output": "", "score": 12604216.792626498}, {"input": "embroidery is to cloth what bracelet is to jewelry", "output": "", "score": 10837381.560826208}, {"input": "embroidery is to cloth what mural is to wall", "output": "", "score": 5815144.9224591}, {"input": "embroidery is to cloth what tattoo is to design", "output": "", "score": 27973732.90302986}, {"input": "embroidery is to cloth what paint is to color", "output": "", "score": 4766263.811706718}, {"input": "embroidery is to cloth what flower is to vase", "output": "", "score": 26960829.200026494}, {"input": "incorrigible is to reformed what unnerving is to irritated", "output": "", "score": 23593031.87425011}, {"input": "incorrigible is to reformed what innocuous is to harmed", "output": "", "score": 18676121.98562025}, {"input": "incorrigible is to reformed what irrelevant is to verified", "output": "", "score": 36727600.60585866}, {"input": "incorrigible is to reformed what insolvent is to dissolved", "output": "", "score": 59019258.483414344}, {"input": "incorrigible is to reformed what indelible is to erased", "output": "", "score": 20768716.805772718}, {"input": "food is to hunger what love is to loneliness", "output": "", "score": 5651300.400360272}, {"input": "food is to hunger what ginseng is to energy", "output": "", "score": 4141292.6939217737}, {"input": "food is to hunger what antiseptic is to wound", "output": "", "score": 11802393.959036825}, {"input": "food is to hunger what anodyne is to pain", "output": "", "score": 16115562.738097634}, {"input": "food is to hunger what no is to choice", "output": "", "score": 3300570.3062146767}, {"input": "word is to language what paint is to portrait", "output": "", "score": 50473266.16160439}, {"input": "word is to language what poetry is to rhythm", "output": "", "score": 90204709.6418766}, {"input": "word is to language what note is to music", "output": "", "score": 18116515.28527197}, {"input": "word is to language what tale is to story", "output": "", "score": 17090259.679709278}, {"input": "word is to language what week is to year", "output": "", "score": 3971377.3152422626}, {"input": "purgation is to impurities what catharsis is to epiphanies", "output": "", "score": 61810237.64039503}, {"input": "purgation is to impurities what sterilization is to ailments", "output": "", "score": 15714399.33471071}, {"input": "purgation is to impurities what salvation is to prayers", "output": "", "score": 28812860.148886375}, {"input": "purgation is to impurities what disinfection is to bacteria", "output": "", "score": 7167649.599105468}, {"input": "purgation is to impurities what inattention is to details", "output": "", "score": 27059676.1996742}, {"input": "wedding is to marriage what birthday is to cake", "output": "", "score": 25960160.14178394}, {"input": "wedding is to marriage what coronation is to reign", "output": "", "score": 53492833.543039255}, {"input": "wedding is to marriage what graduation is to diploma", "output": "", "score": 195041469.65646052}, {"input": "wedding is to marriage what promotion is to job", "output": "", "score": 57202019.03179829}, {"input": "wedding is to marriage what decoration is to bravery", "output": "", "score": 25948862.160296585}, {"input": "puppeteer is to marionette what teacher is to textbook", "output": "", "score": 14106193.392924383}, {"input": "puppeteer is to marionette what ballerina is to leotard", "output": "", "score": 14928691.7971275}, {"input": "puppeteer is to marionette what hypnotist is to subject", "output": "", "score": 17719382.45390904}, {"input": "puppeteer is to marionette what lawyer is to criminal", "output": "", "score": 17225888.203555766}, {"input": "puppeteer is to marionette what manager is to baseball", "output": "", "score": 3544258.686896034}, {"input": "glaze is to pottery what scuff is to furniture", "output": "", "score": 2638006.327867126}, {"input": "glaze is to pottery what donate is to tree", "output": "", "score": 5701617.285392426}, {"input": "glaze is to pottery what ice is to cake", "output": "", "score": 3050249.6528173815}, {"input": "glaze is to pottery what injure is to gun", "output": "", "score": 6367527.940507756}, {"input": "glaze is to pottery what chortle is to laugh", "output": "", "score": 4235014.881113353}, {"input": "pastiche is to writing what collage is to art", "output": "", "score": 6569333.363248426}, {"input": "pastiche is to writing what melody is to music", "output": "", "score": 3457550.552548343}, {"input": "pastiche is to writing what bandage is to medicine", "output": "", "score": 17507818.740526736}, {"input": "pastiche is to writing what school is to philosophy", "output": "", "score": 5762976.653415985}, {"input": "pastiche is to writing what sequel is to film", "output": "", "score": 12159645.522647526}, {"input": "carpenter is to woodwork what guitarist is to pick", "output": "", "score": 11563612.874284994}, {"input": "carpenter is to woodwork what cook is to heat", "output": "", "score": 973684.6196391626}, {"input": "carpenter is to woodwork what sculptor is to studio", "output": "", "score": 7363375.3348144945}, {"input": "carpenter is to woodwork what weaver is to cloth", "output": "", "score": 11200073.529989881}, {"input": "carpenter is to woodwork what potter is to shape", "output": "", "score": 8304360.936117025}, {"input": "flowers is to florist what rings is to jeweler", "output": "", "score": 8934990.475796482}, {"input": "flowers is to florist what pharmacy is to pharmacist", "output": "", "score": 14156764.389080249}, {"input": "flowers is to florist what roses is to arrangement", "output": "", "score": 6088485.261939136}, {"input": "flowers is to florist what wedding is to caterer", "output": "", "score": 4941194.821620593}, {"input": "flowers is to florist what stethoscope is to doctor", "output": "", "score": 13046415.56000962}]